architools/__init__.py
architools/geography.py
architools/server.py
architools/time.py
architools/tui.py
architools/units.py
architools/connectors/__init__.py
architools/connectors/rhino.py
architools/connectors/step.py
architools/connectors/wkt.py
architools/connectors/postgis/__init__.py
architools/connectors/postgis/connection.py
architools/connectors/postgis/query.py
architools/connectors/postgis/template.py
architools/connectors/three/__init__.py
architools/connectors/three/writer.py
architools/context/__init__.py
architools/context/geography.py
architools/context/lot.py
architools/context/scene.py
architools/context/service.py
architools/context/taxlot.py
architools/environment/__init__.py
architools/environment/sun.py
architools/geometry/__init__.py
architools/geometry/boolean.py
architools/geometry/brep.py
architools/geometry/common.py
architools/geometry/conversion.py
architools/geometry/curve.py
architools/geometry/edge.py
architools/geometry/face.py
architools/geometry/healing.py
architools/geometry/measure.py
architools/geometry/outline.py
architools/geometry/point.py
architools/geometry/polygon.py
architools/geometry/reference.py
architools/geometry/surface.py
architools/geometry/topology.py
architools/geometry/vector.py
architools/geometry/volume.py
architools/geometry/wire.py
architools/material/__init__.py
architools/material/color.py
architools/maths/__init__.py
architools/maths/interval.py
architools/ui/__init__.py
architools/ui/commands.py
architools/ui/state.py
architools/ui/viewer.py
architools-0.1.0.dist-info/LICENSE
architools-0.1.0.dist-info/METADATA
architools-0.1.0.dist-info/WHEEL
architools-0.1.0.dist-info/top_level.txt
architools-0.1.0.dist-info/RECORD
